unsupervised_bias_detection/__init__.py
unsupervised_bias_detection/cluster/__init__.py
unsupervised_bias_detection/cluster/_bahc.py
unsupervised_bias_detection/cluster/_cluster_node.py
unsupervised_bias_detection/cluster/_kmeans.py
unsupervised_bias_detection/cluster/_kmodes.py
unsupervised_bias_detection/utils/__init__.py
unsupervised_bias_detection/utils/_get_column_dtypes.py
unsupervised_bias_detection/utils/dataset.py
unsupervised_bias_detection/utils/validation.py
unsupervised_bias_detection-0.2.6.dist-info/LICENSE
unsupervised_bias_detection-0.2.6.dist-info/METADATA
unsupervised_bias_detection-0.2.6.dist-info/WHEEL
unsupervised_bias_detection-0.2.6.dist-info/RECORD
