Metadata-Version: 2.3
Name: unsupervised-bias-detection
Version: 0.2.6
Summary: package for unsupervised bias detection
License: EUPL-1.2 license
Author: NGO Algorithm Audit
Requires-Python: >=3.11,<4.0
Classifier: License :: Other/Proprietary License
Classifier: Programming Language :: Python :: 3
Classifier: Programming Language :: Python :: 3.11
Classifier: Programming Language :: Python :: 3.12
Classifier: Programming Language :: Python :: 3.13
Requires-Dist: kmodes (>=0.12.2,<0.13.0)
Requires-Dist: numpy (>=1.26.4,<2.0.0)
Requires-Dist: scikit-learn (>=1.6.1)
